{
  "youthGroups": [
    {
      "id": "1",
      "parish": "St. Michael's Cathedral",
      "leader": "Sarah Johnson",
      "seminarianSgl": "Fr. John Smith",
      "phone": "555-123-4567",
      "maleTeens": 25,
      "femaleTeens": 30,
      "maleChaperones": 4,
      "femaleChaperones": 5,
      "stayingOffCampus": false,
      "specialAccommodations": "Two students require wheelchair accessible rooms"
    },
    {
      "id": "2",
      "parish": "Holy Trinity Parish (OC)",
      "leader": "Robert Williams",
      "seminarianSgl": "Fr. Michael Davis",
      "phone": "555-234-5678",
      "maleTeens": 18,
      "femaleTeens": 22,
      "maleChaperones": 3,
      "femaleChaperones": 4,
      "stayingOffCampus": true,
      "specialAccommodations": "Staying at nearby hotel - attending all day events"
    },
    {
      "id": "3",
      "parish": "Sacred Heart Church",
      "leader": "Mary Thompson",
      "seminarianSgl": "",
      "phone": "555-345-6789",
      "maleTeens": 15,
      "femaleTeens": 20,
      "maleChaperones": 2,
      "femaleChaperones": 3,
      "stayingOffCampus": false,
      "specialAccommodations": "One chaperone has CPAP machine"
    },
    {
      "id": "4",
      "parish": "St. Patrick's Parish",
      "leader": "James Martinez",
      "seminarianSgl": "Fr. Thomas Anderson",
      "phone": "555-456-7890",
      "maleTeens": 12,
      "femaleTeens": 15,
      "maleChaperones": 2,
      "femaleChaperones": 2,
      "stayingOffCampus": false,
      "specialAccommodations": ""
    },
    {
      "id": "5",
      "parish": "Our Lady of Grace (OC)",
      "leader": "Jennifer Brown",
      "seminarianSgl": "",
      "phone": "555-567-8901",
      "maleTeens": 8,
      "femaleTeens": 10,
      "maleChaperones": 1,
      "femaleChaperones": 2,
      "stayingOffCampus": true,
      "specialAccommodations": "Commuting from local parish house"
    },
    {
      "id": "6",
      "parish": "St. Joseph's Cathedral",
      "leader": "David Lee",
      "seminarianSgl": "Fr. Patrick Wilson",
      "phone": "555-678-9012",
      "maleTeens": 20,
      "femaleTeens": 25,
      "maleChaperones": 3,
      "femaleChaperones": 4,
      "stayingOffCampus": false,
      "specialAccommodations": "Food allergies: 2 students allergic to peanuts"
    }
  ],
  "housingRooms": [
    {
      "building": "Knott Academic Center",
      "roomId": "320",
      "gender": "male",
      "capacity": 32,
      "accessibility": "Wheelchair accessible, ground floor"
    },
    {
      "building": "Knott Academic Center",
      "roomId": "327",
      "gender": "male",
      "capacity": 32,
      "accessibility": ""
    },
    {
      "building": "Knott Academic Center",
      "roomId": "311",
      "gender": "male",
      "capacity": 35,
      "accessibility": ""
    },
    {
      "building": "ARCC",
      "roomId": "Gym Floor East",
      "gender": "female",
      "capacity": 150,
      "accessibility": ""
    },
    {
      "building": "ARCC",
      "roomId": "Gym Floor West",
      "gender": "female",
      "capacity": 150,
      "accessibility": "Wheelchair accessible entrance"
    },
    {
      "building": "Off Campus",
      "roomId": "Male",
      "gender": "male",
      "capacity": 500,
      "accessibility": ""
    },
    {
      "building": "Off Campus",
      "roomId": "Female",
      "gender": "female",
      "capacity": 500,
      "accessibility": ""
    }
  ],
  "smallGroupRooms": [
    {
      "building": "Knott Academic Center",
      "roomId": "304",
      "gender": "mixed",
      "capacity": 26,
      "features": "Projector available"
    },
    {
      "building": "Knott Academic Center",
      "roomId": "308",
      "gender": "mixed",
      "capacity": 33,
      "features": "Whiteboard and tables"
    },
    {
      "building": "Knott Academic Center",
      "roomId": "310",
      "gender": "mixed",
      "capacity": 44,
      "features": "Large conference table"
    },
    {
      "building": "Knott Academic Center",
      "roomId": "207",
      "gender": "mixed",
      "capacity": 25,
      "features": ""
    },
    {
      "building": "COAD Science Building",
      "roomId": "158",
      "gender": "mixed",
      "capacity": 60,
      "features": "Open wall - chairs needed"
    },
    {
      "building": "Student Center",
      "roomId": "Meeting Room A",
      "gender": "mixed",
      "capacity": 30,
      "features": "Round tables, comfortable seating"
    }
  ],
  "housingAssignments": {
    "male": {
      "1": ["Knott Academic Center-320"],
      "3": ["Knott Academic Center-327"],
      "4": ["Knott Academic Center-311"],
      "6": ["Knott Academic Center-320", "Knott Academic Center-327"]
    },
    "female": {
      "1": ["ARCC-Gym Floor East"],
      "3": ["ARCC-Gym Floor West"],
      "4": ["ARCC-Gym Floor East"],
      "6": ["ARCC-Gym Floor West"]
    }
  },
  "smallGroupAssignments": {
    "1": ["Knott Academic Center-304"],
    "2": ["Knott Academic Center-308"],
    "3": ["Knott Academic Center-310"],
    "4": ["Knott Academic Center-207"],
    "5": ["COAD Science Building-158"],
    "6": ["Student Center-Meeting Room A"]
  },
  "mealColorAssignments": {
    "1": "Blue",
    "2": "Red",
    "3": "Orange",
    "4": "Yellow",
    "5": "Green",
    "6": "Purple"
  },
  "mealTimes": {
    "Blue": {
      "friDinner": "5:30 PM",
      "satBreakfast": "7:00 AM",
      "satLunch": "12:00 PM",
      "satDinner": "5:30 PM",
      "sunBreakfast": "7:30 AM"
    },
    "Red": {
      "friDinner": "6:00 PM",
      "satBreakfast": "7:30 AM",
      "satLunch": "12:30 PM",
      "satDinner": "6:00 PM",
      "sunBreakfast": "8:00 AM"
    },
    "Orange": {
      "friDinner": "6:30 PM",
      "satBreakfast": "8:00 AM",
      "satLunch": "1:00 PM",
      "satDinner": "6:30 PM",
      "sunBreakfast": "8:30 AM"
    },
    "Yellow": {
      "friDinner": "7:00 PM",
      "satBreakfast": "8:30 AM",
      "satLunch": "1:30 PM",
      "satDinner": "7:00 PM",
      "sunBreakfast": "9:00 AM"
    },
    "Green": {
      "friDinner": "5:30 PM",
      "satBreakfast": "7:00 AM",
      "satLunch": "12:00 PM",
      "satDinner": "5:30 PM",
      "sunBreakfast": "7:30 AM"
    },
    "Purple": {
      "friDinner": "6:00 PM",
      "satBreakfast": "7:30 AM",
      "satLunch": "12:30 PM",
      "satDinner": "6:00 PM",
      "sunBreakfast": "8:00 AM"
    },
    "Brown": {
      "friDinner": "6:30 PM",
      "satBreakfast": "8:00 AM",
      "satLunch": "1:00 PM",
      "satDinner": "6:30 PM",
      "sunBreakfast": "8:30 AM"
    },
    "Grey": {
      "friDinner": "7:00 PM",
      "satBreakfast": "8:30 AM",
      "satLunch": "1:30 PM",
      "satDinner": "7:00 PM",
      "sunBreakfast": "9:00 AM"
    }
  },
  "defaultNotes": {
    "generalInfo": "Welcome to Mount 2000 Youth Retreat 2026! Please check in at the main desk upon arrival. All meals will be served in the dining hall. Emergency contact number: 555-911-HELP",
    "housingNotes": "Lights out at 11:00 PM. Wake up call at 6:30 AM. Please keep noise levels down after 10:00 PM. No food in sleeping areas. Leave rooms clean and tidy.",
    "teenShowerPlan": "Teen showers available in Knott Academic Center basement from 10:00 PM - 11:00 PM (Friday) and 6:30 AM - 7:30 AM (Saturday/Sunday). Please bring your own toiletries and towels. Shower times are staggered by meal color.",
    "adultShowerPlan": "Adult chaperone showers available in ARCC locker rooms. Access code will be provided at check-in. Available 9:00 PM - 12:00 AM and 6:00 AM - 8:00 AM."
  },
  "groupNotes": {
    "1": "VIP group - early check-in arranged. Will arrive Friday at 3:00 PM.",
    "3": "Requested to be near bathroom facilities due to medical needs.",
    "6": "Large group - may need additional supervision during activities."
  },
  "timestamp": "2026-01-15T14:30:00.000Z",
  "version": "3.0"
}
